eb_deploy_docker-0.0.1.dist-info/METADATA
eb_deploy_docker-0.0.1.dist-info/RECORD
eb_deploy_docker-0.0.1.dist-info/WHEEL
eb_deploy_docker-0.0.1.dist-info/entry_points.txt
eb_deploy_docker-0.0.1.dist-info/top_level.txt
src/__init__.py
src/eb_deploy_docker.py
