Metadata-Version: 2.1
Name: eb-deploy-docker
Version: 0.0.1
Summary: A command line utility to deploy to Elastic Beanstalk Docker platforms
Home-page: https://github.com/manuelcarrizo/eb-deploy-docker
Author: Manuel Carrizo
Author-email: manuelcarrizo@gmail.com
License: MIT
Platform: UNKNOWN
Classifier: Development Status :: 4 - Beta
Classifier: Intended Audience :: System Administrators
Classifier: License :: OSI Approved :: MIT License
Classifier: Programming Language :: Python :: 3.6
Requires-Dist: awsebcli
Requires-Dist: boto3
Requires-Dist: pyaml
